scrapyspiderstats/__init__.py
scrapyspiderstats/__version__.py
scrapyspiderstats/extension.py
scrapy_spiderstats_extension-0.0.2.dist-info/METADATA
scrapy_spiderstats_extension-0.0.2.dist-info/WHEEL
scrapy_spiderstats_extension-0.0.2.dist-info/top_level.txt
scrapy_spiderstats_extension-0.0.2.dist-info/RECORD
