Metadata-Version: 2.1
Name: scrapy-spiderstats-extension
Version: 0.0.2
Summary: Scrapy Spider Stats to MongoDB Extension
Home-page: https://github.com/crawlaio/scrapy-spiderstats-extension
Author: Sitoi
Author-email: 133397418@qq.com
License: MIT
Platform: UNKNOWN
Classifier: License :: OSI Approved :: MIT License
Classifier: Programming Language :: Python :: 3.6
Classifier: Programming Language :: Python :: 3.7
Classifier: Programming Language :: Python :: 3.8
Classifier: Programming Language :: Python :: Implementation :: CPython
Classifier: Programming Language :: Python :: Implementation :: PyPy
Requires-Python: >=3.6.0
Requires-Dist: pymongo
Requires-Dist: twisted
